bravocapital/__init__.py
fambd2015b/__init__.py
fambd2015b-0.3.dist-info/DESCRIPTION.rst
fambd2015b-0.3.dist-info/METADATA
fambd2015b-0.3.dist-info/RECORD
fambd2015b-0.3.dist-info/WHEEL
fambd2015b-0.3.dist-info/metadata.json
fambd2015b-0.3.dist-info/top_level.txt
