Metadata-Version: 2.0
Name: fambd2015b
Version: 0.3
Summary: Python package for Financial Analytics!
Home-page: https://github.com/my13/fa_mbd_2015b
Author: TEAM B - Master Big Data
Author-email: jldelgadodavara@student.ie.edu
License: MIT
Platform: UNKNOWN
